greypredict/GreyPredictionModel.py
greypredict/SequenceCheck.py
greypredict/__init__.py
greypredict-0.0.1.data/scripts/demo.py
greypredict-0.0.1.dist-info/LICENSE
greypredict-0.0.1.dist-info/METADATA
greypredict-0.0.1.dist-info/WHEEL
greypredict-0.0.1.dist-info/top_level.txt
greypredict-0.0.1.dist-info/RECORD
